{
  "version": 1,
  "domain": "zoositioweb.com.mx",
  "aliases": [
    "zoositioweb.com"
  ],
  "defaultPageId": "default",
  "notFoundPageId": "default",
  "routes": [
    {
      "path": "/",
      "pageId": "default",
      "label": "Inicio"
    },
    {
      "path": "/acceso",
      "pageId": "acceso",
      "label": "Acceso"
    },
    {
      "path": "/auth/callback",
      "pageId": "auth-callback",
      "label": "Auth callback"
    },
    {
      "path": "/mi-cuenta",
      "pageId": "mi-cuenta",
      "label": "Mi cuenta",
      "auth": {
        "required": true,
        "redirectTo": "/acceso",
        "allowedGroups": [
          "zoosite-client",
          "zoosite-admin"
        ]
      }
    }
  ],
  "site": {
    "appIdentity": {
      "identifier": "zoositiowebcommx",
      "name": "zoositioweb"
    },
    "theme": {
      "palettes": {
        "light": {
          "bgColor": "#ffffff",
          "textColor": "#111111",
          "titleColor": "#111111",
          "linkColor": "#0d6efd",
          "accentColor": "#128c7e",
          "secondaryBgColor": "#f5f5f5",
          "secondaryTextColor": "#222222",
          "secondaryTitleColor": "#111111",
          "secondaryLinkColor": "#0d6efd",
          "secondaryAccentColor": "#25d366",
          "successColor": "#128c7e",
          "onSuccessColor": "#06110f",
          "errorColor": "#dc3545",
          "onErrorColor": "#3b0a10",
          "warningColor": "#f59e0b",
          "onWarningColor": "#3a2400",
          "infoColor": "#214c72",
          "onInfoColor": "#041b44"
        },
        "dark": {
          "bgColor": "#11161d",
          "textColor": "#edf3f8",
          "titleColor": "#ffffff",
          "linkColor": "#6097b5",
          "accentColor": "#25d366",
          "secondaryBgColor": "#1d2630",
          "secondaryTextColor": "#c2ccd6",
          "secondaryTitleColor": "#f7fbff",
          "secondaryLinkColor": "#6097b5",
          "secondaryAccentColor": "#ff8c7a",
          "successColor": "#128c7e",
          "onSuccessColor": "#06110f",
          "errorColor": "#ff7b89",
          "onErrorColor": "#31070c",
          "warningColor": "#f7c948",
          "onWarningColor": "#2a1f00",
          "infoColor": "#6097b5",
          "onInfoColor": "#071b33"
        }
      }
    },
    "i18n": {
      "defaultLanguage": "es",
      "supportedLanguages": [
        "es"
      ]
    }
  },
  "runtime": {
    "authRemote": {
      "enabled": true,
      "authProfileId": "staff",
      "endpoint": "/auth/runtime-config"
    },
    "navigation": {
      "scrollRestoration": {
        "mode": "top",
        "behavior": "auto"
      }
    }
  }
}
